Workbook

Sheet Leia-me
A1: Argus — Catálogo de Dados
A2: Fonte única das séries de cada aba. Vira o arquivo de configuração do pipeline na Fase 1.
A5: Como usar
A6: Brasil / EUA | B6: Uma linha por indicador. Filtre por Aba, Fase ou Status. As colunas Fase e Status têm lista suspensa e podem ser editadas.
A7: Central | B7: Blocos da aba Central (Command Center) e do agregador de notícias.
A8: Fontes | B8: Registro de cada fonte: acesso, autenticação, limites e risco técnico.
A9: Resumo | B9: Contagens por aba, fase e status, calculadas por fórmula.
A11: Status
A12: Verificado | B12: Código conferido nesta sessão contra o portal oficial (título ou último valor).
A13: Confirmar | B13: Código conhecido, ainda não conferido. A validação automática da Fase 0 confirma título e última observação.
A14: A mapear | B14: Fonte definida, código ainda não localizado.
A15: Sem API | B15: Dado gratuito, mas só por download manual ou PDF. Entra como carga manual ou fica para v2.
A16: Pago | B16: Exige licença. A coluna Observação indica o substituto gratuito quando existe.
A17: Derivado | B17: Calculado pelo Argus a partir de outras séries. A fórmula está em Código / endpoint.
A18: Curado | B18: Tabela mantida manualmente (decisões do Copom, metas, pesquisas).
A20: Fase
A21: MVP | B21: Brasil + Central. Fontes oficiais com API, sem modelagem própria.
A22: EUA | B22: Logo após o MVP: mesmo template de abas, quase tudo via FRED.
A23: v2 | B23: Fontes difíceis (B3, ANBIMA, pesquisas, texto) ou modelos próprios.
A24: v3 | B24: Projetos de maior risco: NLP de discursos, fluxo B3, balanços CVM.
A26: Tipo | B26: Define quais transformações o motor de gráfico oferece. Ex.: taxa nunca vira acumulado 12m; variação mensal é encadeada, não somada.
A27: Data | B27: Planilha gerada a partir dos CSVs em docs/catalogo/. Edite os CSVs e rode o gerador; resultado da validação em validacao.md.

Sheet Resumo
A1: Resumo do catálogo
A2: Contagens calculadas a partir das abas Brasil e EUA.
A5: Brasil
A6: Aba | B6: MVP | C6: EUA | D6: v2 | E6: v3 | F6: Total | H6: Status | I6: Qtd
A7: Atividade | B7: =COUNTIFS(Brasil!$B$6:$B$146,$A7,Brasil!$K$6:$K$146,"MVP") | C7: =COUNTIFS(Brasil!$B$6:$B$146,$A7,Brasil!$K$6:$K$146,"EUA") | D7: =COUNTIFS(Brasil!$B$6:$B$146,$A7,Brasil!$K$6:$K$146,"v2") | E7: =COUNTIFS(Brasil!$B$6:$B$146,$A7,Brasil!$K$6:$K$146,"v3") | F7: =SUM(B7:E7) | H7: Verificado | I7: =COUNTIF(Brasil!$L$6:$L$146,H7)
A8: Mercado de Trabalho | B8: =COUNTIFS(Brasil!$B$6:$B$146,$A8,Brasil!$K$6:$K$146,"MVP") | C8: =COUNTIFS(Brasil!$B$6:$B$146,$A8,Brasil!$K$6:$K$146,"EUA") | D8: =COUNTIFS(Brasil!$B$6:$B$146,$A8,Brasil!$K$6:$K$146,"v2") | E8: =COUNTIFS(Brasil!$B$6:$B$146,$A8,Brasil!$K$6:$K$146,"v3") | F8: =SUM(B8:E8) | H8: Confirmar | I8: =COUNTIF(Brasil!$L$6:$L$146,H8)
A9: Inflação | B9: =COUNTIFS(Brasil!$B$6:$B$146,$A9,Brasil!$K$6:$K$146,"MVP") | C9: =COUNTIFS(Brasil!$B$6:$B$146,$A9,Brasil!$K$6:$K$146,"EUA") | D9: =COUNTIFS(Brasil!$B$6:$B$146,$A9,Brasil!$K$6:$K$146,"v2") | E9: =COUNTIFS(Brasil!$B$6:$B$146,$A9,Brasil!$K$6:$K$146,"v3") | F9: =SUM(B9:E9) | H9: A mapear | I9: =COUNTIF(Brasil!$L$6:$L$146,H9)
A10: Política Monetária | B10: =COUNTIFS(Brasil!$B$6:$B$146,$A10,Brasil!$K$6:$K$146,"MVP") | C10: =COUNTIFS(Brasil!$B$6:$B$146,$A10,Brasil!$K$6:$K$146,"EUA") | D10: =COUNTIFS(Brasil!$B$6:$B$146,$A10,Brasil!$K$6:$K$146,"v2") | E10: =COUNTIFS(Brasil!$B$6:$B$146,$A10,Brasil!$K$6:$K$146,"v3") | F10: =SUM(B10:E10) | H10: Sem API | I10: =COUNTIF(Brasil!$L$6:$L$146,H10)
A11: Fiscal | B11: =COUNTIFS(Brasil!$B$6:$B$146,$A11,Brasil!$K$6:$K$146,"MVP") | C11: =COUNTIFS(Brasil!$B$6:$B$146,$A11,Brasil!$K$6:$K$146,"EUA") | D11: =COUNTIFS(Brasil!$B$6:$B$146,$A11,Brasil!$K$6:$K$146,"v2") | E11: =COUNTIFS(Brasil!$B$6:$B$146,$A11,Brasil!$K$6:$K$146,"v3") | F11: =SUM(B11:E11) | H11: Pago | I11: =COUNTIF(Brasil!$L$6:$L$146,H11)
A12: Setor Externo | B12: =COUNTIFS(Brasil!$B$6:$B$146,$A12,Brasil!$K$6:$K$146,"MVP") | C12: =COUNTIFS(Brasil!$B$6:$B$146,$A12,Brasil!$K$6:$K$146,"EUA") | D12: =COUNTIFS(Brasil!$B$6:$B$146,$A12,Brasil!$K$6:$K$146,"v2") | E12: =COUNTIFS(Brasil!$B$6:$B$146,$A12,Brasil!$K$6:$K$146,"v3") | F12: =SUM(B12:E12) | H12: Derivado | I12: =COUNTIF(Brasil!$L$6:$L$146,H12)
A13: Famílias | B13: =COUNTIFS(Brasil!$B$6:$B$146,$A13,Brasil!$K$6:$K$146,"MVP") | C13: =COUNTIFS(Brasil!$B$6:$B$146,$A13,Brasil!$K$6:$K$146,"EUA") | D13: =COUNTIFS(Brasil!$B$6:$B$146,$A13,Brasil!$K$6:$K$146,"v2") | E13: =COUNTIFS(Brasil!$B$6:$B$146,$A13,Brasil!$K$6:$K$146,"v3") | F13: =SUM(B13:E13) | H13: Curado | I13: =COUNTIF(Brasil!$L$6:$L$146,H13)
A14: Empresas | B14: =COUNTIFS(Brasil!$B$6:$B$146,$A14,Brasil!$K$6:$K$146,"MVP") | C14: =COUNTIFS(Brasil!$B$6:$B$146,$A14,Brasil!$K$6:$K$146,"EUA") | D14: =COUNTIFS(Brasil!$B$6:$B$146,$A14,Brasil!$K$6:$K$146,"v2") | E14: =COUNTIFS(Brasil!$B$6:$B$146,$A14,Brasil!$K$6:$K$146,"v3") | F14: =SUM(B14:E14)
A15: Mercado & Risco | B15: =COUNTIFS(Brasil!$B$6:$B$146,$A15,Brasil!$K$6:$K$146,"MVP") | C15: =COUNTIFS(Brasil!$B$6:$B$146,$A15,Brasil!$K$6:$K$146,"EUA") | D15: =COUNTIFS(Brasil!$B$6:$B$146,$A15,Brasil!$K$6:$K$146,"v2") | E15: =COUNTIFS(Brasil!$B$6:$B$146,$A15,Brasil!$K$6:$K$146,"v3") | F15: =SUM(B15:E15)
A16: Política | B16: =COUNTIFS(Brasil!$B$6:$B$146,$A16,Brasil!$K$6:$K$146,"MVP") | C16: =COUNTIFS(Brasil!$B$6:$B$146,$A16,Brasil!$K$6:$K$146,"EUA") | D16: =COUNTIFS(Brasil!$B$6:$B$146,$A16,Brasil!$K$6:$K$146,"v2") | E16: =COUNTIFS(Brasil!$B$6:$B$146,$A16,Brasil!$K$6:$K$146,"v3") | F16: =SUM(B16:E16)
A17: Análises | B17: =COUNTIFS(Brasil!$B$6:$B$146,$A17,Brasil!$K$6:$K$146,"MVP") | C17: =COUNTIFS(Brasil!$B$6:$B$146,$A17,Brasil!$K$6:$K$146,"EUA") | D17: =COUNTIFS(Brasil!$B$6:$B$146,$A17,Brasil!$K$6:$K$146,"v2") | E17: =COUNTIFS(Brasil!$B$6:$B$146,$A17,Brasil!$K$6:$K$146,"v3") | F17: =SUM(B17:E17)
A18: Central | B18: =COUNTIFS(Brasil!$B$6:$B$146,$A18,Brasil!$K$6:$K$146,"MVP") | C18: =COUNTIFS(Brasil!$B$6:$B$146,$A18,Brasil!$K$6:$K$146,"EUA") | D18: =COUNTIFS(Brasil!$B$6:$B$146,$A18,Brasil!$K$6:$K$146,"v2") | E18: =COUNTIFS(Brasil!$B$6:$B$146,$A18,Brasil!$K$6:$K$146,"v3") | F18: =SUM(B18:E18)
A19: Total | B19: =SUM(B7:B18) | C19: =SUM(C7:C18) | D19: =SUM(D7:D18) | E19: =SUM(E7:E18) | F19: =SUM(F7:F18)
A21: EUA
A22: Aba | B22: MVP | C22: EUA | D22: v2 | E22: v3 | F22: Total | H22: Status | I22: Qtd
A23: Mercado de Trabalho | B23: =COUNTIFS(EUA!$B$6:$B$101,$A23,EUA!$K$6:$K$101,"MVP") | C23: =COUNTIFS(EUA!$B$6:$B$101,$A23,EUA!$K$6:$K$101,"EUA") | D23: =COUNTIFS(EUA!$B$6:$B$101,$A23,EUA!$K$6:$K$101,"v2") | E23: =COUNTIFS(EUA!$B$6:$B$101,$A23,EUA!$K$6:$K$101,"v3") | F23: =SUM(B23:E23) | H23: Verificado | I23: =COUNTIF(EUA!$L$6:$L$101,H23)
A24: Inflação | B24: =COUNTIFS(EUA!$B$6:$B$101,$A24,EUA!$K$6:$K$101,"MVP") | C24: =COUNTIFS(EUA!$B$6:$B$101,$A24,EUA!$K$6:$K$101,"EUA") | D24: =COUNTIFS(EUA!$B$6:$B$101,$A24,EUA!$K$6:$K$101,"v2") | E24: =COUNTIFS(EUA!$B$6:$B$101,$A24,EUA!$K$6:$K$101,"v3") | F24: =SUM(B24:E24) | H24: Confirmar | I24: =COUNTIF(EUA!$L$6:$L$101,H24)
A25: Atividade | B25: =COUNTIFS(EUA!$B$6:$B$101,$A25,EUA!$K$6:$K$101,"MVP") | C25: =COUNTIFS(EUA!$B$6:$B$101,$A25,EUA!$K$6:$K$101,"EUA") | D25: =COUNTIFS(EUA!$B$6:$B$101,$A25,EUA!$K$6:$K$101,"v2") | E25: =COUNTIFS(EUA!$B$6:$B$101,$A25,EUA!$K$6:$K$101,"v3") | F25: =SUM(B25:E25) | H25: A mapear | I25: =COUNTIF(EUA!$L$6:$L$101,H25)
A26: Fed & Juros | B26: =COUNTIFS(EUA!$B$6:$B$101,$A26,EUA!$K$6:$K$101,"MVP") | C26: =COUNTIFS(EUA!$B$6:$B$101,$A26,EUA!$K$6:$K$101,"EUA") | D26: =COUNTIFS(EUA!$B$6:$B$101,$A26,EUA!$K$6:$K$101,"v2") | E26: =COUNTIFS(EUA!$B$6:$B$101,$A26,EUA!$K$6:$K$101,"v3") | F26: =SUM(B26:E26) | H26: Sem API | I26: =COUNTIF(EUA!$L$6:$L$101,H26)
A27: Imobiliário | B27: =COUNTIFS(EUA!$B$6:$B$101,$A27,EUA!$K$6:$K$101,"MVP") | C27: =COUNTIFS(EUA!$B$6:$B$101,$A27,EUA!$K$6:$K$101,"EUA") | D27: =COUNTIFS(EUA!$B$6:$B$101,$A27,EUA!$K$6:$K$101,"v2") | E27: =COUNTIFS(EUA!$B$6:$B$101,$A27,EUA!$K$6:$K$101,"v3") | F27: =SUM(B27:E27) | H27: Pago | I27: =COUNTIF(EUA!$L$6:$L$101,H27)
A28: Consumidor | B28: =COUNTIFS(EUA!$B$6:$B$101,$A28,EUA!$K$6:$K$101,"MVP") | C28: =COUNTIFS(EUA!$B$6:$B$101,$A28,EUA!$K$6:$K$101,"EUA") | D28: =COUNTIFS(EUA!$B$6:$B$101,$A28,EUA!$K$6:$K$101,"v2") | E28: =COUNTIFS(EUA!$B$6:$B$101,$A28,EUA!$K$6:$K$101,"v3") | F28: =SUM(B28:E28) | H28: Derivado | I28: =COUNTIF(EUA!$L$6:$L$101,H28)
A29: Corporativo | B29: =COUNTIFS(EUA!$B$6:$B$101,$A29,EUA!$K$6:$K$101,"MVP") | C29: =COUNTIFS(EUA!$B$6:$B$101,$A29,EUA!$K$6:$K$101,"EUA") | D29: =COUNTIFS(EUA!$B$6:$B$101,$A29,EUA!$K$6:$K$101,"v2") | E29: =COUNTIFS(EUA!$B$6:$B$101,$A29,EUA!$K$6:$K$101,"v3") | F29: =SUM(B29:E29) | H29: Curado | I29: =COUNTIF(EUA!$L$6:$L$101,H29)
A30: Setor Externo & Fiscal | B30: =COUNTIFS(EUA!$B$6:$B$101,$A30,EUA!$K$6:$K$101,"MVP") | C30: =COUNTIFS(EUA!$B$6:$B$101,$A30,EUA!$K$6:$K$101,"EUA") | D30: =COUNTIFS(EUA!$B$6:$B$101,$A30,EUA!$K$6:$K$101,"v2") | E30: =COUNTIFS(EUA!$B$6:$B$101,$A30,EUA!$K$6:$K$101,"v3") | F30: =SUM(B30:E30)
A31: Risco & Mercado | B31: =COUNTIFS(EUA!$B$6:$B$101,$A31,EUA!$K$6:$K$101,"MVP") | C31: =COUNTIFS(EUA!$B$6:$B$101,$A31,EUA!$K$6:$K$101,"EUA") | D31: =COUNTIFS(EUA!$B$6:$B$101,$A31,EUA!$K$6:$K$101,"v2") | E31: =COUNTIFS(EUA!$B$6:$B$101,$A31,EUA!$K$6:$K$101,"v3") | F31: =SUM(B31:E31)
A32: Total | B32: =SUM(B23:B31) | C32: =SUM(C23:C31) | D32: =SUM(D23:D31) | E32: =SUM(E23:E31) | F32: =SUM(F23:F31)

Sheet Brasil
A1: Brasil — catálogo de séries
A2: Subabas da aba Brasil. Foco do MVP.
A5: ID | B5: Aba | C5: Bloco | D5: Indicador | E5: Fonte | F5: Código / endpoint | G5: Frequência | H5: Unidade | I5: Tipo | J5: Transformações válidas | K5: Fase | L5: Status | M5: Observação
A6: BR-001 | B6: Atividade | C6: PIB | D6: PIB real — índice de volume (SA) | E6: IBGE SIDRA | F6: t1621/v584/c11255=90707 | G6: Trimestral | H6: Índice | I6: Índice | J6: Nível, MoM, QoQ, YoY, acum. 3/6/9/12m, 3m/6m SAAR, real/nominal | K6: MVP | L6: Verificado | M6: Série encadeada com ajuste sazonal; base para QoQ SAAR
A7: BR-002 | B7: Atividade | C7: PIB | D7: PIB real — taxas (QoQ, YoY, acum. 4T) | E7: IBGE SIDRA | F7: t5932/v6561,6562,6564/c11255=90707 | G7: Trimestral | H7: % | I7: Taxa | J7: Nível, Δ p.p. (MoM, YoY, 3/6/12m) | K7: MVP | L7: Verificado | M7: Taxas oficiais; usar para conferir cálculo próprio
A8: BR-003 | B8: Atividade | C8: PIB | D8: PIB — ótica da oferta (agro, indústria, serviços) | E8: IBGE SIDRA | F8: t1621/v584/c11255=90687,90691,90696 | G8: Trimestral | H8: Índice | I8: Índice | J8: Nível, MoM, QoQ, YoY, acum. 3/6/9/12m, 3m/6m SAAR, real/nominal | K8: MVP | L8: Verificado
A9: BR-004 | B9: Atividade | C9: PIB | D9: PIB — ótica da demanda (C, G, FBCF, X, M) | E9: IBGE SIDRA | F9: t1621/v584/c11255=93404,93405,93406,93407,93408 | G9: Trimestral | H9: Índice | I9: Índice | J9: Nível, MoM, QoQ, YoY, acum. 3/6/9/12m, 3m/6m SAAR, real/nominal | K9: MVP | L9: Verificado | M9: Consumo das famílias também alimenta a aba Famílias
A10: BR-005 | B10: Atividade | C10: PIB | D10: PIB nominal acumulado 12m (R$) | E10: BCB SGS | F10: 4382 | G10: Mensal | H10: R$ mi | I10: Fluxo | J10: Nível, soma 3/12m, MoM % (SA), YoY %, real/nominal, % PIB | K10: MVP | L10: Verificado | M10: Denominador de todas as razões % PIB
A11: BR-006 | B11: Atividade | C11: Mensais | D11: IBC-Br (SA) | E11: BCB SGS | F11: 24364 | G11: Mensal | H11: Índice | I11: Índice | J11: Nível, MoM, QoQ, YoY, acum. 3/6/9/12m, 3m/6m SAAR, real/nominal | K11: MVP | L11: Verificado | M11: Sem ajuste: 24363
A12: BR-007 | B12: Atividade | C12: Mensais | D12: Produção industrial — PIM-PF (geral, extrativa, transformação) | E12: IBGE SIDRA | F12: t8888/v12606,12607/c544=129314,129315,129316 ; t8888/v11602,11604/c544=129314 | G12: Mensal | H12: Índice | I12: Índice | J12: Nível, MoM, QoQ, YoY, acum. 3/6/9/12m, 3m/6m SAAR, real/nominal | K12: MVP | L12: Verificado | M12: Tabela nova (base 2022); conferir na Fase 0; v11602 (YoY) e v11604 (12 meses) são as taxas oficiais, usadas para conferir o cálculo do site
A13: BR-008 | B13: Atividade | C13: Mensais | D13: Varejo restrito e ampliado — PMC | E13: IBGE SIDRA | F13: t8880/v7169,7170/c11046=56733,56734 ; t8881/v7169,7170/c11046=56735,56736 ; t8880/v11708/c11046=56734 | G13: Mensal | H13: Índice | I13: Índice | J13: Nível, MoM, QoQ, YoY, acum. 3/6/9/12m, 3m/6m SAAR, real/nominal | K13: MVP | L13: Verificado | M13: Volume e receita nominal; t8880 v11708 (MoM SA oficial) confere o cálculo do site
A14: BR-009 | B14: Atividade | C14: Mensais | D14: Volume de serviços — PMS | E14: IBGE SIDRA | F14: t5906/v7167,7168/c11046=56725,56726 | G14: Mensal | H14: Índice | I14: Índice | J14: Nível, MoM, QoQ, YoY, acum. 3/6/9/12m, 3m/6m SAAR, real/nominal | K14: MVP | L14: Verificado
A15: BR-010 | B15: Atividade | C15: Mensais | D15: Utilização da capacidade instalada (NUCI) | E15: FGV IBRE / CNI | F15: — | G15: Mensal | H15: % | I15: Taxa | J15: Nível, Δ p.p. (MoM, YoY, 3/6/12m) | K15: v2 | L15: Sem API | M15: FGV restringe dados; CNI publica xlsx
A16: BR-011 | B16: Atividade | C16: Confiança | D16: Confiança FGV (consumidor, indústria, serviços, comércio) | E16: FGV IBRE | F16: — | G16: Mensal | H16: Índice | I16: Índice | J16: Nível, MoM, QoQ, YoY, acum. 3/6/9/12m, 3m/6m SAAR, real/nominal | K16: v2 | L16: Sem API | M16: Sem API aberta; download manual ou assinatura
A17: BR-012 | B17: Atividade | C17: Coincidentes | D17: Produção de veículos (Anfavea) | E17: Anfavea | F17: — | G17: Mensal | H17: Unidades | I17: Fluxo | J17: Nível, soma 3/12m, MoM % (SA), YoY %, real/nominal, % PIB | K17: v2 | L17: Sem API | M17: xlsx no site
A18: BR-013 | B18: Atividade | C18: Coincidentes | D18: Carga de energia (ONS) | E18: ONS Dados Abertos | F18: — | G18: Diária | H18: MWmed | I18: Fluxo | J18: Nível, soma 3/12m, MoM % (SA), YoY %, real/nominal, % PIB | K18: v2 | L18: A mapear | M18: Proxy de atividade de alta frequência
A19: BR-014 | B19: Atividade | C19: Expectativas | D19: Focus — PIB (ano corrente e seguinte) | E19: BCB Olinda (Focus) | F19: ExpectativasMercadoAnuais · Indicador='PIB Total' | G19: Semanal | H19: % | I19: Taxa | J19: Nível, Δ p.p. (MoM, YoY, 3/6/12m) | K19: MVP | L19: Verificado | M19: Mediana, desvio e nº de respondentes
A20: BR-015 | B20: Mercado de Trabalho | C20: PNAD | D20: Taxa de desocupação | E20: BCB SGS / IBGE SIDRA | F20: 24369 / t6381 | G20: Mensal (trim. móvel) | H20: % | I20: Taxa | J20: Nível, Δ p.p. (MoM, YoY, 3/6/12m) | K20: MVP | L20: Verificado | M20: Série oficial sem ajuste sazonal; SA própria (X-13) na v2
A21: BR-016 | B21: Mercado de Trabalho | C21: PNAD | D21: Taxa de participação e nível de ocupação | E21: IBGE SIDRA | F21: t5944/v4096 ; t6379/v4097 | G21: Mensal (trim. móvel) | H21: % | I21: Taxa | J21: Nível, Δ p.p. (MoM, YoY, 3/6/12m) | K21: MVP | L21: Verificado | M21: PNAD Contínua mensal: t5944 participação, t6379 nível da ocupação
A22: BR-017 | B22: Mercado de Trabalho | C22: PNAD | D22: População ocupada (total, formal, informal) | E22: IBGE SIDRA | F22: t8501/v4090/c1350=57302,57303 | G22: Mensal (trim. móvel) | H22: Mil pessoas | I22: Estoque | J22: Nível, MoM %, YoY %, real/nominal, % PIB | K22: MVP | L22: Verificado | M22: PNAD Contínua mensal, por situação de informalidade
A23: BR-018 | B23: Mercado de Trabalho | C23: PNAD | D23: Taxa de informalidade | E23: IBGE SIDRA | F23: t8513/v12466 | G23: Mensal (trim. móvel) | H23: % | I23: Taxa | J23: Nível, Δ p.p. (MoM, YoY, 3/6/12m) | K23: MVP | L23: Verificado | M23: PNAD Contínua mensal
A24: BR-019 | B24: Mercado de Trabalho | C24: PNAD | D24: Rendimento médio real habitual | E24: IBGE SIDRA | F24: t6390/v5933,5929 | G24: Mensal (trim. móvel) | H24: R$ | I24: Índice | J24: Nível, MoM, QoQ, YoY, acum. 3/6/9/12m, 3m/6m SAAR, real/nominal | K24: MVP | L24: Verificado | M24: Equivalente a AHE/real wage dos EUA
A25: BR-020 | B25: Mercado de Trabalho | C25: PNAD | D25: Massa de rendimento real habitual | E25: IBGE SIDRA | F25: t6392/v6293,6288 | G25: Mensal (trim. móvel) | H25: R$ mi | I25: Fluxo | J25: Nível, soma 3/12m, MoM % (SA), YoY %, real/nominal, % PIB | K25: MVP | L25: Verificado | M25: PNAD Contínua mensal, habitualmente recebido; liga Trabalho a Consumo
A26: BR-021 | B26: Mercado de Trabalho | C26: PNAD | D26: Subutilização, desalentados, desemprego de longo prazo | E26: IBGE SIDRA | F26: PNAD Contínua trimestral | G26: Trimestral | H26: % | I26: Taxa | J26: Nível, Δ p.p. (MoM, YoY, 3/6/12m) | K26: v2 | L26: A mapear | M26: Equivalente ao U6 dos EUA
... A32: BR-027 | B32: Inflação | C32: Cheio | D32: IPCA-15 | E32: BCB SGS | F32: 7478 | G32: Mensal | H32: % m/m | I32: Var % mensal | J32: Mensal, acum. 3/6/9/12m (encadeado), 3m/6m anualizado, YoY via 12m | K32: MVP | L32: Verificado | M32: Prévia
A33: BR-028 | B33: Inflação | C33: Cheio | D33: INPC | E33: BCB SGS | F33: 188 | G33: Mensal | H33: % m/m | I33: Var % mensal | J33: Mensal, acum. 3/6/9/12m (encadeado), 3m/6m anualizado, YoY via 12m | K33: v2 | L33: Confirmar
A34: BR-029 | B34: Inflação | C34: Núcleos | D34: Núcleo médias aparadas sem suavização (MA) | E34: BCB SGS | F34: 11426 | G34: Mensal | H34: % m/m | I34: Var % mensal | J34: Mensal, acum. 3/6/9/12m (encadeado), 3m/6m anualizado, YoY via 12m | K34: MVP | L34: Verificado
A35: BR-030 | B35: Inflação | C35: Núcleos | D35: Núcleo médias aparadas com suavização (MS) | E35: BCB SGS | F35: 4466 | G35: Mensal | H35: % m/m | I35: Var % mensal | J35: Mensal, acum. 3/6/9/12m (encadeado), 3m/6m anualizado, YoY via 12m | K35: MVP | L35: Verificado
A36: BR-031 | B36: Inflação | C36: Núcleos | D36: Núcleo por exclusão EX0 (sem monitorados e alim. domicílio) | E36: BCB SGS | F36: 11427 | G36: Mensal | H36: % m/m | I36: Var % mensal | J36: Mensal, acum. 3/6/9/12m (encadeado), 3m/6m anualizado, YoY via 12m | K36: MVP | L36: Verificado
A37: BR-032 | B37: Inflação | C37: Núcleos | D37: Núcleo por exclusão EX2 | E37: BCB SGS | F37: 27838 | G37: Mensal | H37: % m/m | I37: Var % mensal | J37: Mensal, acum. 3/6/9/12m (encadeado), 3m/6m anualizado, YoY via 12m | K37: MVP | L37: Verificado | M37: NT 57 (dez/2025, Tabela 11): EX1 = 16121 e EX2 = 27838; o título SGS de 16121 ('ex2') é enganoso; validador 2026-10-04: título oficial confere
A38: BR-033 | B38: Inflação | C38: Núcleos | D38: Núcleo de dupla ponderação (DP) | E38: BCB SGS | F38: 16122 | G38: Mensal | H38: % m/m | I38: Var % mensal | J38: Mensal, acum. 3/6/9/12m (encadeado), 3m/6m anualizado, YoY via 12m | K38: MVP | L38: Verificado
A39: BR-034 | B39: Inflação | C39: Núcleos | D39: Núcleos EX3 e P55 | E39: BCB SGS | F39: 27839 / 28750 | G39: Mensal | H39: % m/m | I39: Var % mensal | J39: Mensal, acum. 3/6/9/12m (encadeado), 3m/6m anualizado, YoY via 12m | K39: MVP | L39: Verificado | M39: Títulos SGS: "Núcleo por exclusão - EX3" (27839) e "Núcleo Percentil 55" (28750); sondagem 2026-10-04
A40: BR-126 | B40: Inflação | C40: Núcleos | D40: Núcleo ex-alimentação e energia (EX-FE) | E40: BCB SGS | F40: 28751 | G40: Mensal | H40: % m/m | I40: Var % mensal | J40: Mensal, acum. 3/6/9/12m (encadeado), 3m/6m anualizado, YoY via 12m | K40: MVP | L40: Verificado | M40: Título SGS 28751: "Núcleo Ex-alimentação e energia (EX-FE)"; comparável ao core dos EUA
A41: BR-127 | B41: Inflação | C41: Núcleos | D41: Média dos 5 núcleos do Copom (EX0, EX3, MS, DP, P55) | E41: Argus | F41: média(11427, 27839, 4466, 16122, 28750) | G41: Mensal | H41: % m/m | I41: Derivado | J41: Mensal, acum. 3/6/9/12m (encadeado), 3m/6m anualizado, YoY via 12m | K41: MVP | L41: Derivado | M41: Leitura-síntese citada pelo Copom; recalcular e conferir contra o RPM
A42: BR-128 | B42: Inflação | C42: Núcleos | D42: Mediana ponderada do IPCA (P50) | E42: Argus | F42: f(t7060): subitens ordenados por variação, peso acumulado = 50% | G42: Mensal | H42: % m/m | I42: Derivado | J42: Mensal, acum. 3/6/9/12m (encadeado), 3m/6m anualizado, YoY via 12m | K42: MVP | L42: Derivado | M42: Método do P55 do BCB (NT 57) em 50%; o mesmo cálculo em 55% reproduz o SGS 28750 em 80 de 80 meses (2020-2026). Desde 2020 (tabela 7060)
A43: BR-129 | B43: Inflação | C43: Núcleos | D43: Bens industriais subjacentes (EX3 Industriais) | E43: BCB SGS | F43: 29684 | G43: Mensal | H43: % m/m | I43: Var % mensal | J43: Mensal, acum. 3/6/9/12m (encadeado), 3m/6m anualizado, YoY via 12m | K43: MVP | L43: Verificado | M43: Série oficial do BCB desde a NT 57 (dez/2025, Tabela 11): antes era cálculo próprio; validador 2026-10-04: título oficial confere
A44: BR-130 | B44: Inflação | C44: Núcleos | D44: Serviços intensivos em trabalho | E44: Argus | F44: f(t7060): subitens de serviços com alto peso de mão de obra | G44: Mensal | H44: % m/m | I44: Derivado | J44: Mensal, acum. 3/6/9/12m (encadeado), 3m/6m anualizado, YoY via 12m | K44: MVP | L44: Derivado | M44: Lista de subitens curada a partir da classificação do BCB; ligação com Mercado de Trabalho
A45: BR-131 | B45: Inflação | C45: Núcleos | D45: Preços rígidos × flexíveis (sticky/flexible) | E45: Argus | F45: f(t7060 + classificação por frequência de reajuste) | G45: Mensal | H45: % m/m | I45: Derivado | J45: Mensal, acum. 3/6/9/12m (encadeado), 3m/6m anualizado, YoY via 12m | K45: v2 | L45: Derivado | M45: Estilo Fed de Atlanta; exige montar a classificação de subitens
A46: BR-035 | B46: Inflação | C46: Aberturas | D46: Preços livres | E46: BCB SGS | F46: 11428 | G46: Mensal | H46: % m/m | I46: Var % mensal | J46: Mensal, acum. 3/6/9/12m (encadeado), 3m/6m anualizado, YoY via 12m | K46: MVP | L46: Verificado
A47: BR-036 | B47: Inflação | C47: Aberturas | D47: Preços monitorados | E47: BCB SGS | F47: 4449 | G47: Mensal | H47: % m/m | I47: Var % mensal | J47: Mensal, acum. 3/6/9/12m (encadeado), 3m/6m anualizado, YoY via 12m | K47: MVP | L47: Verificado
A48: BR-037 | B48: Inflação | C48: Aberturas | D48: Serviços | E48: BCB SGS | F48: 10844 | G48: Mensal | H48: % m/m | I48: Var % mensal | J48: Mensal, acum. 3/6/9/12m (encadeado), 3m/6m anualizado, YoY via 12m | K48: MVP | L48: Verificado
A49: BR-038 | B49: Inflação | C49: Aberturas | D49: Bens industriais e alimentação no domicílio | E49: BCB SGS | F49: 27863 / 27864 | G49: Mensal | H49: % m/m | I49: Var % mensal | J49: Mensal, acum. 3/6/9/12m (encadeado), 3m/6m anualizado, YoY via 12m | K49: MVP | L49: Verificado
A50: BR-039 | B50: Inflação | C50: Aberturas | D50: Comercializáveis e não comercializáveis | E50: BCB SGS | F50: 4447 / 4448 | G50: Mensal | H50: % m/m | I50: Var % mensal | J50: Mensal, acum. 3/6/9/12m (encadeado), 3m/6m anualizado, YoY via 12m | K50: v2 | L50: Confirmar
A51: BR-040 | B51: Inflação | C51: Aberturas | D51: Índice de difusão | E51: BCB SGS | F51: 21379 | G51: Mensal | H51: % | I51: Taxa | J51: Nível, Δ p.p. (MoM, YoY, 3/6/12m) | K51: MVP | L51: Verificado
A52: BR-041 | B52: Inflação | C52: Aberturas | D52: IPCA por subitem e peso | E52: IBGE SIDRA | F52: t7060/v63,66/c315=all | G52: Mensal | H52: % m/m e peso | I52: Var % mensal | J52: Mensal, acum. 3/6/9/12m (encadeado), 3m/6m anualizado, YoY via 12m | K52: MVP | L52: Verificado | M52: Base para calcular serviços subjacentes, supercore BR e aberturas próprias
A53: BR-042 | B53: Inflação | C53: Aberturas | D53: Serviços subjacentes (EX3 Serviços) | E53: BCB SGS | F53: 29683 | G53: Mensal | H53: % m/m | I53: Var % mensal | J53: Mensal, acum. 3/6/9/12m (encadeado), 3m/6m anualizado, YoY via 12m | K53: MVP | L53: Verificado | M53: Série oficial do BCB desde a NT 57 (dez/2025, Tabela 11): antes era cálculo próprio; validador 2026-10-04: título oficial confere
A54: BR-043 | B54: Inflação | C54: Atacado | D54: IGP-M e IGP-DI | E54: BCB SGS | F54: 189 / 190 | G54: Mensal | H54: % m/m | I54: Var % mensal | J54: Mensal, acum. 3/6/9/12m (encadeado), 3m/6m anualizado, YoY via 12m | K54: MVP | L54: Verificado | M54: Equivalente ao PPI na ótica de preços ao produtor
A55: BR-044 | B55: Inflação | C55: Atacado | D55: IPA (atacado) e INCC | E55: BCB SGS | F55: A mapear | G55: Mensal | H55: % m/m | I55: Var % mensal | J55: Mensal, acum. 3/6/9/12m (encadeado), 3m/6m anualizado, YoY via 12m | K55: v2 | L55: A mapear
A56: BR-045 | B56: Inflação | C56: Atacado | D56: IC-Br — índice de commodities BCB (total, agro, metal, energia) | E56: BCB SGS | F56: 27574–27577 | G56: Mensal | H56: Índice | I56: Índice | J56: Nível, MoM, QoQ, YoY, acum. 3/6/9/12m, 3m/6m SAAR, real/nominal | K56: MVP | L56: Verificado | M56: Equivalente a container freight/commodities como indicador antecedente
A57: BR-046 | B57: Inflação | C57: Expectativas | D57: Focus — IPCA (ano corrente, seguinte, +2, +3) | E57: BCB Olinda (Focus) | F57: ExpectativasMercadoAnuais · Indicador='IPCA' | G57: Semanal | H57: % | I57: Taxa | J57: Nível, Δ p.p. (MoM, YoY, 3/6/12m) | K57: MVP | L57: Verificado
A58: BR-047 | B58: Inflação | C58: Expectativas | D58: Focus — IPCA 12 meses à frente | E58: BCB Olinda (Focus) | F58: ExpectativasMercadoInflacao12Meses · Indicador='IPCA' | G58: Diária | H58: % | I58: Taxa | J58: Nível, Δ p.p. (MoM, YoY, 3/6/12m) | K58: MVP | L58: Verificado | M58: Série suavizada; usada no juro real ex-ante
A59: BR-048 | B59: Inflação | C59: Expectativas | D59: Inflação implícita (breakeven) prefixado × NTN-B | E59: Tesouro Transparente | F59: Taxas históricas do Tesouro Direto (CSV) | G59: Diária | H59: % | I59: Taxa | J59: Nível, Δ p.p. (MoM, YoY, 3/6/12m) | K59: v2 | L59: Confirmar | M59: Equivalente ao 5y5y dos EUA
A60: BR-049 | B60: Inflação | C60: Meta | D60: Meta de inflação e intervalo de tolerância | E60: BCB / CMN | F60: Curado | G60: Anual | H60: % | I60: Taxa | J60: Nível, Δ p.p. (MoM, YoY, 3/6/12m) | K60: MVP | L60: Curado | M60: Tabela própria; meta contínua desde 2025
A61: BR-050 | B61: Política Monetária | C61: Juros | D61: Meta Selic definida pelo Copom | E61: BCB SGS | F61: 432 | G61: Diária | H61: % a.a. | I61: Taxa | J61: Nível, Δ p.p. (MoM, YoY, 3/6/12m) | K61: MVP | L61: Verificado | M61: Fonte dos ciclos do Copom; o SGS registra a meta vigente até a próxima reunião (data futura é normal)
A62: BR-051 | B62: Política Monetária | C62: Juros | D62: Selic efetiva diária | E62: BCB SGS | F62: 11 | G62: Diária | H62: % a.d. | I62: Taxa | J62: Nível, Δ p.p. (MoM, YoY, 3/6/12m) | K62: v2 | L62: Verificado | M62: Confirmado no portal BCB
A63: BR-052 | B63: Política Monetária | C63: Juros | D63: Selic anualizada base 252 | E63: BCB SGS | F63: 1178 | G63: Diária | H63: % a.a. | I63: Taxa | J63: Nível, Δ p.p. (MoM, YoY, 3/6/12m) | K63: MVP | L63: Verificado | M63: Confirmado no portal BCB; limite de 10 anos por consulta
A64: BR-053 | B64: Política Monetária | C64: Juros | D64: Selic acumulada no mês anualizada | E64: BCB SGS | F64: 4189 | G64: Mensal | H64: % a.a. | I64: Taxa | J64: Nível, Δ p.p. (MoM, YoY, 3/6/12m) | K64: MVP | L64: Verificado | M64: Respondeu 13,83 em 09/2026
A65: BR-054 | B65: Política Monetária | C65: Juros | D65: CDI anualizado base 252 | E65: BCB SGS | F65: 4389 | G65: Diária | H65: % a.a. | I65: Taxa | J65: Nível, Δ p.p. (MoM, YoY, 3/6/12m) | K65: v2 | L65: Confirmar
A66: BR-055 | B66: Política Monetária | C66: Juros | D66: Juro real ex-ante (proxy) | E66: Argus | F66: f(432, Focus IPCA 12m) | G66: Diária | H66: % a.a. | I66: Derivado | J66: Conforme definição da fórmula | K66: MVP | L66: Derivado | M66: v2: trocar por swap DI 360 deflacionado
A67: BR-056 | B67: Política Monetária | C67: Expectativas | D67: Focus — Selic por reunião do Copom | E67: BCB Olinda (Focus) | F67: ExpectativasMercadoSelic | G67: Semanal | H67: % a.a. | I67: Taxa | J67: Nível, Δ p.p. (MoM, YoY, 3/6/12m) | K67: MVP | L67: Verificado | M67: Equivalente ao WIRP/dotplot
A68: BR-057 | B68: Política Monetária | C68: Copom | D68: Histórico de decisões (data, decisão, bps, unanimidade) | E68: BCB + SGS 432 | F68: Curado | G68: Por reunião | H68: bps | I68: Evento | J68: — | K68: MVP | L68: Curado | M68: Dataset próprio, conferido contra o SGS
A69: BR-058 | B69: Política Monetária | C69: Copom | D69: Comunicados e atas (texto) | E69: BCB site (API Copom) | F69: comunicados ; atas | G69: Por reunião | H69: Texto | I69: Texto | J69: — | K69: MVP | L69: Verificado | M69: API do site do BCB, não documentada (copom/comunicados, copom/atas e *_detalhes); texto convertido para texto puro na tabela events; comunicados desde a 46ª reunião (2000)
A70: BR-059 | B70: Política Monetária | C70: Agregados | D70: M1 (saldo fim de período, SA) | E70: BCB SGS | F70: 27841 | G70: Mensal | H70: R$ mil | I70: Estoque | J70: Nível, MoM %, YoY %, real/nominal, % PIB | K70: MVP | L70: Verificado | M70: Sem ajuste: 27791
A71: BR-060 | B71: Política Monetária | C71: Agregados | D71: M2 (saldo fim de período, SA) | E71: BCB SGS | F71: 27842 | G71: Mensal | H71: R$ mil | I71: Estoque | J71: Nível, MoM %, YoY %, real/nominal, % PIB | K71: MVP | L71: Verificado | M71: Sem ajuste: 27810
A72: BR-061 | B72: Política Monetária | C72: Agregados | D72: M3 e M4 (saldo fim de período) | E72: BCB SGS | F72: 27813 / 27815 | G72: Mensal | H72: R$ mil | I72: Estoque | J72: Nível, MoM %, YoY %, real/nominal, % PIB | K72: MVP | L72: Verificado
A73: BR-062 | B73: Política Monetária | C73: Crédito | D73: Saldo de crédito total, PF e PJ | E73: BCB SGS | F73: 20539 / 20541 / 20540 | G73: Mensal | H73: R$ mi | I73: Estoque | J73: Nível, MoM %, YoY %, real/nominal, % PIB | K73: MVP | L73: Verificado
A74: BR-063 | B74: Política Monetária | C74: Crédito | D74: Saldo livre × direcionado | E74: BCB SGS | F74: 20542 / 20593 | G74: Mensal | H74: R$ mi | I74: Estoque | J74: Nível, MoM %, YoY %, real/nominal, % PIB | K74: MVP | L74: Verificado | M74: Transmissão da Selic ocorre no livre
A75: BR-064 | B75: Política Monetária | C75: Crédito | D75: Concessões total, PF e PJ | E75: BCB SGS | F75: 20631 / 20633 / 20632 | G75: Mensal | H75: R$ mi | I75: Fluxo | J75: Nível, soma 3/12m, MoM % (SA), YoY %, real/nominal, % PIB | K75: MVP | L75: Verificado
A76: BR-065 | B76: Política Monetária | C76: Crédito | D76: Taxa média de juros total, PF e PJ | E76: BCB SGS | F76: 20714 / 20716 / 20715 | G76: Mensal | H76: % a.a. | I76: Taxa | J76: Nível, Δ p.p. (MoM, YoY, 3/6/12m) | K76: MVP | L76: Verificado
A77: BR-066 | B77: Política Monetária | C77: Crédito | D77: Spread médio total | E77: BCB SGS | F77: 20783 | G77: Mensal | H77: p.p. | I77: Taxa | J77: Nível, Δ p.p. (MoM, YoY, 3/6/12m) | K77: MVP | L77: Verificado
A78: BR-067 | B78: Política Monetária | C78: Crédito | D78: Indicador de custo do crédito (ICC) | E78: BCB SGS | F78: 25351 | G78: Mensal | H78: % a.a. | I78: Taxa | J78: Nível, Δ p.p. (MoM, YoY, 3/6/12m) | K78: v2 | L78: Confirmar
A79: BR-068 | B79: Política Monetária | C79: Condições | D79: Índice de condições financeiras BR | E79: Argus | F79: f(juros, câmbio, bolsa, spread) | G79: Diária | H79: Índice | I79: Derivado | J79: Conforme definição da fórmula | K79: v2 | L79: Derivado | M79: Equivalente ao NFCI
A80: BR-069 | B80: Fiscal | C80: Resultado | D80: Resultado primário do setor público consolidado — 12m % PIB | E80: BCB SGS | F80: 5793 | G80: Mensal | H80: % PIB | I80: Taxa | J80: Nível, Δ p.p. (MoM, YoY, 3/6/12m) | K80: MVP | L80: Verificado
A81: BR-070 | B81: Fiscal | C81: Resultado | D81: Resultado nominal e juros nominais — 12m % PIB | E81: BCB SGS | F81: 5727 / 5760 | G81: Mensal | H81: % PIB | I81: Taxa | J81: Nível, Δ p.p. (MoM, YoY, 3/6/12m) | K81: MVP | L81: Verificado | M81: 5727 resultado nominal, 5760 juros nominais; NFSP sem desvalorização cambial, 12m % PIB
A82: BR-071 | B82: Fiscal | C82: Resultado | D82: Primário por esfera (Gov. Central, regionais, estatais) | E82: BCB SGS | F82: 5783 / 5789 | G82: Mensal | H82: % PIB | I82: Taxa | J82: Nível, Δ p.p. (MoM, YoY, 3/6/12m) | K82: MVP | L82: Verificado | M82: 5783 Governo Federal e BC, 5789 estatais (12m % PIB); governos regionais: código a localizar
A83: BR-072 | B83: Fiscal | C83: Dívida | D83: Dívida bruta do governo geral (DBGG) % PIB | E83: BCB SGS | F83: 13762 | G83: Mensal | H83: % PIB | I83: Taxa | J83: Nível, Δ p.p. (MoM, YoY, 3/6/12m) | K83: MVP | L83: Verificado
A84: BR-073 | B84: Fiscal | C84: Dívida | D84: Dívida líquida do setor público (DLSP) % PIB | E84: BCB SGS | F84: 4513 | G84: Mensal | H84: % PIB | I84: Taxa | J84: Nível, Δ p.p. (MoM, YoY, 3/6/12m) | K84: MVP | L84: Verificado
A85: BR-074 | B85: Fiscal | C85: Gov. Central | D85: Receitas e despesas do Governo Central (RTN) | E85: Tesouro Nacional (API RTN) | F85: rtn=10.01.1 ; rtn=10.02.1 ; rtn=10.01.2 ; rtn=10.03.1 ; rtn=10.04.1 ; rtn=10.08.1 ; rtn=10.09.1 | G85: Mensal | H85: R$ mi | I85: Fluxo | J85: Nível, soma 3/12m, MoM % (SA), YoY %, real/nominal, % PIB | K85: MVP | L85: Verificado | M85: API Séries Temporais do RTN (decisão 0010): receita total, transferências, receita líquida, despesa total, primário, juros e nominal; R$ milhões correntes
A86: BR-075 | B86: Fiscal | C86: Gov. Central | D86: Meta de primário e bandas do arcabouço | E86: Tesouro / LDO | F86: Curado | G86: Anual | H86: % PIB | I86: Taxa | J86: Nível, Δ p.p. (MoM, YoY, 3/6/12m) | K86: MVP | L86: Curado
A87: BR-076 | B87: Fiscal | C87: Dívida | D87: Composição e prazo médio da DPF | E87: Tesouro Transparente | F87: RMD (xlsx) | G87: Mensal | H87: % | I87: Taxa | J87: Nível, Δ p.p. (MoM, YoY, 3/6/12m) | K87: v2 | L87: Confirmar
A88: BR-077 | B88: Fiscal | C88: Projeções | D88: Focus — primário e dívida líquida | E88: BCB Olinda (Focus) | F88: ExpectativasMercadoAnuais · Indicador='Resultado primário' ; Indicador='Dívida líquida do setor público' | G88: Semanal | H88: % PIB | I88: Taxa | J88: Nível, Δ p.p. (MoM, YoY, 3/6/12m) | K88: MVP | L88: Verificado
A89: BR-078 | B89: Fiscal | C89: Projeções | D89: Projeções da IFI (cenários) | E89: IFI / Senado | F89: Relatórios (manual) | G89: Mensal | H89: % PIB | I89: Taxa | J89: Nível, Δ p.p. (MoM, YoY, 3/6/12m) | K89: v2 | L89: Sem API | M89: Equivalente às projeções do CBO
A90: BR-079 | B90: Setor Externo | C90: Balança | D90: Exportações, importações e saldo | E90: ComexStat (MDIC) | F90: fluxo=export ; fluxo=import | G90: Mensal | H90: US$ FOB | I90: Fluxo | J90: Nível, soma 3/12m, MoM % (SA), YoY %, real/nominal, % PIB | K90: MVP | L90: Verificado | M90: Dados até 2026-08 (sondagem 2026-10-04). Também semanal
A91: BR-080 | B91: Setor Externo | C91: Balança | D91: Exportações por destino (China, EUA, UE) | E91: ComexStat (MDIC) | F91: fluxo=export/pais=160 ; fluxo=export/pais=249 ; fluxo=export/bloco=22 | G91: Mensal | H91: US$ FOB | I91: Fluxo | J91: Nível, soma 3/12m, MoM % (SA), YoY %, real/nominal, % PIB | K91: MVP | L91: Verificado | M91: Exposição a China e tarifas; Abertura por produto (SH4/NCM) fica para a v2
A92: BR-081 | B92: Setor Externo | C92: BP | D92: Transações correntes | E92: BCB SGS | F92: 22701 | G92: Mensal | H92: US$ mi | I92: Fluxo | J92: Nível, soma 3/12m, MoM % (SA), YoY %, real/nominal, % PIB | K92: MVP | L92: Verificado
A93: BR-082 | B93: Setor Externo | C93: BP | D93: Transações correntes — 12m % PIB | E93: BCB SGS | F93: 23079 | G93: Mensal | H93: % PIB | I93: Taxa | J93: Nível, Δ p.p. (MoM, YoY, 3/6/12m) | K93: MVP | L93: Verificado | M93: Transações correntes acumulado em 12 meses em relação ao PIB
A94: BR-083 | B94: Setor Externo | C94: BP | D94: Investimento direto no país (IDP) | E94: BCB SGS | F94: 22885 | G94: Mensal | H94: US$ mi | I94: Fluxo | J94: Nível, soma 3/12m, MoM % (SA), YoY %, real/nominal, % PIB | K94: MVP | L94: Verificado
A95: BR-084 | B95: Setor Externo | C95: Reservas | D95: Reservas internacionais (conceito caixa, diária) | E95: BCB SGS | F95: 13621 | G95: Diária | H95: US$ mi | I95: Estoque | J95: Nível, MoM %, YoY %, real/nominal, % PIB | K95: MVP | L95: Verificado | M95: Confirmado no portal BCB
A96: BR-085 | B96: Setor Externo | C96: Câmbio | D96: Taxa de câmbio livre — dólar americano (venda) | E96: BCB SGS | F96: 1 | G96: Diária | H96: R$/US$ | I96: Índice | J96: Nível, MoM, QoQ, YoY, acum. 3/6/9/12m, 3m/6m SAAR, real/nominal | K96: MVP | L96: Verificado | M96: Título oficial SGS 1: "Taxa de câmbio - Livre - Dólar americano (venda) - diário"
A97: BR-086 | B97: Setor Externo | C97: Câmbio | D97: Taxa de câmbio efetiva real | E97: BCB SGS | F97: 11752 | G97: Mensal | H97: Índice | I97: Índice | J97: Nível, MoM, QoQ, YoY, acum. 3/6/9/12m, 3m/6m SAAR, real/nominal | K97: MVP | L97: Verificado
A98: BR-087 | B98: Setor Externo | C98: Câmbio | D98: Fluxo cambial (comercial e financeiro) | E98: BCB SGS | F98: A mapear | G98: Semanal | H98: US$ mi | I98: Fluxo | J98: Nível, soma 3/12m, MoM % (SA), YoY %, real/nominal, % PIB | K98: v2 | L98: A mapear
A99: BR-088 | B99: Setor Externo | C99: Câmbio | D99: Focus — câmbio fim de ano | E99: BCB Olinda (Focus) | F99: ExpectativasMercadoAnuais · Indicador='Câmbio' | G99: Semanal | H99: R$/US$ | I99: Índice | J99: Nível, MoM, QoQ, YoY, acum. 3/6/9/12m, 3m/6m SAAR, real/nominal | K99: MVP | L99: Verificado
A100: BR-089 | B100: Setor Externo | C100: Commodities | D100: Minério de ferro, petróleo Brent, soja | E100: FRED | F100: PIORECRUSDM / DCOILBRENTEU / PSOYBUSDM | G100: Mensal/Diária | H100: US$ | I100: Índice | J100: Nível, MoM, QoQ, YoY, acum. 3/6/9/12m, 3m/6m SAAR, real/nominal | K100: MVP | L100: Verificado
A101: BR-090 | B101: Setor Externo | C101: Commodities | D101: Termos de troca | E101: FUNCEX / Ipeadata | F101: A mapear | G101: Mensal | H101: Índice | I101: Índice | J101: Nível, MoM, QoQ, YoY, acum. 3/6/9/12m, 3m/6m SAAR, real/nominal | K101: v2 | L101: A mapear
A102: BR-091 | B102: Famílias | C102: Balanço | D102: Endividamento das famílias com o SFN (% renda 12m) | E102: BCB SGS | F102: 29037 | G102: Mensal | H102: % | I102: Taxa | J102: Nível, Δ p.p. (MoM, YoY, 3/6/12m) | K102: MVP | L102: Verificado | M102: Ex-habitacional: 29038
A103: BR-092 | B103: Famílias | C103: Balanço | D103: Comprometimento de renda com serviço da dívida | E103: BCB SGS | F103: 29034 | G103: Mensal | H103: % | I103: Taxa | J103: Nível, Δ p.p. (MoM, YoY, 3/6/12m) | K103: MVP | L103: Verificado | M103: Equivalente a debt service % DPI
A104: BR-093 | B104: Famílias | C104: Crédito | D104: Cartão de crédito total (PF) | E104: BCB SGS | F104: 20590 | G104: Mensal | H104: R$ mi | I104: Estoque | J104: Nível, MoM %, YoY %, real/nominal, % PIB | K104: MVP | L104: Verificado
A105: BR-094 | B105: Famílias | C105: Crédito | D105: Crédito pessoal total (PF) | E105: BCB SGS | F105: 20580 | G105: Mensal | H105: R$ mi | I105: Estoque | J105: Nível, MoM %, YoY %, real/nominal, % PIB | K105: MVP | L105: Verificado
A106: BR-095 | B106: Famílias | C106: Crédito | D106: Financiamento imobiliário (PF) | E106: BCB SGS | F106: 20612 | G106: Mensal | H106: R$ mi | I106: Estoque | J106: Nível, MoM %, YoY %, real/nominal, % PIB | K106: MVP | L106: Verificado
A107: BR-096 | B107: Famílias | C107: Crédito | D107: Inadimplência PF | E107: BCB SGS | F107: 21084 | G107: Mensal | H107: % | I107: Taxa | J107: Nível, Δ p.p. (MoM, YoY, 3/6/12m) | K107: MVP | L107: Verificado
...

Sheet EUA
A1: EUA — catálogo de séries
A2: Mapeamento da planilha original de dados US para fonte e código.
A5: ID | B5: Aba | C5: Bloco | D5: Indicador | E5: Fonte | F5: Código / endpoint | G5: Frequência | H5: Unidade | I5: Tipo | J5: Transformações válidas | K5: Fase | L5: Status | M5: Observação
A6: US-001 | B6: Mercado de Trabalho | C6: Payroll | D6: Non-farm Payrolls | E6: FRED (BLS) | F6: PAYEMS | G6: Mensal | H6: Mil | I6: Estoque | J6: Nível, MoM %, YoY %, real/nominal, % PIB | K6: EUA | L6: Verificado
A7: US-002 | B7: Mercado de Trabalho | C7: Desemprego | D7: Unemployment Rate (U3) | E7: FRED (BLS) | F7: UNRATE | G7: Mensal | H7: % | I7: Taxa | J7: Nível, Δ p.p. (MoM, YoY, 3/6/12m) | K7: EUA | L7: Verificado
A8: US-003 | B8: Mercado de Trabalho | C8: Desemprego | D8: Unemployment Breakdown (U6, demografia) | E8: FRED (BLS) | F8: U6RATE + séries LNS140000xx | G8: Mensal | H8: % | I8: Taxa | J8: Nível, Δ p.p. (MoM, YoY, 3/6/12m) | K8: EUA | L8: Verificado
A9: US-004 | B9: Mercado de Trabalho | C9: Participação | D9: Labour Force Participation (total e 25–54) | E9: FRED (BLS) | F9: CIVPART / LNS11300060 | G9: Mensal | H9: % | I9: Taxa | J9: Nível, Δ p.p. (MoM, YoY, 3/6/12m) | K9: EUA | L9: Verificado
A10: US-005 | B10: Mercado de Trabalho | C10: JOLTS | D10: Job Openings to Unemployed Ratio | E10: Argus | F10: JTSJOL / UNEMPLOY | G10: Mensal | H10: x | I10: Derivado | J10: Conforme definição da fórmula | K10: EUA | L10: Derivado
A11: US-006 | B11: Mercado de Trabalho | C11: JOLTS | D11: JOLTS Openings, Hires, Quits, Layoffs | E11: FRED (BLS) | F11: JTSJOL / JTSHIL / JTSQUL / JTSLDL | G11: Mensal | H11: Mil | I11: Fluxo | J11: Nível, soma 3/12m, MoM % (SA), YoY %, real/nominal, % PIB | K11: EUA | L11: Verificado
A12: US-007 | B12: Mercado de Trabalho | C12: Claims | D12: Jobless Claims (Initial & Continuing) | E12: FRED (DOL) | F12: ICSA / CCSA | G12: Semanal | H12: Mil | I12: Fluxo | J12: Nível, soma 3/12m, MoM % (SA), YoY %, real/nominal, % PIB | K12: EUA | L12: Verificado
A13: US-008 | B13: Mercado de Trabalho | C13: Pesquisas | D13: Jobs Hard to Find (Conference Board) | E13: Conference Board | F13: — | G13: Mensal | H13: % | I13: Taxa | J13: Nível, Δ p.p. (MoM, YoY, 3/6/12m) | K13: v2 | L13: Pago | M13: Proxy gratuita: nenhuma equivalente direta
A14: US-009 | B14: Mercado de Trabalho | C14: Pesquisas | D14: NFIB Job Openings Hard to Fill / Hiring Plans | E14: NFIB | F14: Relatório mensal (PDF) | G14: Mensal | H14: % | I14: Taxa | J14: Nível, Δ p.p. (MoM, YoY, 3/6/12m) | K14: v2 | L14: Sem API
A15: US-010 | B15: Mercado de Trabalho | C15: Indicadores | D15: Beveridge Curve | E15: Argus | F15: UNRATE × JTSJOR | G15: Mensal | H15: % | I15: Derivado | J15: Conforme definição da fórmula | K15: EUA | L15: Derivado
A16: US-011 | B16: Mercado de Trabalho | C16: Salários | D16: Employment Cost Index | E16: FRED (BLS) | F16: ECIALLCIV | G16: Trimestral | H16: Índice | I16: Índice | J16: Nível, MoM, QoQ, YoY, acum. 3/6/9/12m, 3m/6m SAAR, real/nominal | K16: EUA | L16: Verificado
A17: US-012 | B17: Mercado de Trabalho | C17: Salários | D17: Average Hourly Earnings | E17: FRED (BLS) | F17: CES0500000003 | G17: Mensal | H17: US$ | I17: Índice | J17: Nível, MoM, QoQ, YoY, acum. 3/6/9/12m, 3m/6m SAAR, real/nominal | K17: EUA | L17: Verificado
A18: US-013 | B18: Mercado de Trabalho | C18: Salários | D18: Real Wage Growth | E18: Argus | F18: f(CES0500000003, CPIAUCSL) | G18: Mensal | H18: % | I18: Derivado | J18: Conforme definição da fórmula | K18: EUA | L18: Derivado
A19: US-014 | B19: Mercado de Trabalho | C19: Salários | D19: Wage Growth Tracker (job switcher) | E19: Atlanta Fed | F19: Download (xlsx) | G19: Mensal | H19: % | I19: Taxa | J19: Nível, Δ p.p. (MoM, YoY, 3/6/12m) | K19: v2 | L19: Sem API | M19: Não encontrado no FRED com o código testado
A20: US-015 | B20: Mercado de Trabalho | C20: Indicadores | D20: Sahm Rule (real-time) | E20: FRED | F20: SAHMREALTIME | G20: Mensal | H20: p.p. | I20: Taxa | J20: Nível, Δ p.p. (MoM, YoY, 3/6/12m) | K20: EUA | L20: Verificado | M20: 0,00 p.p. em 09/2026
A21: US-016 | B21: Inflação | C21: CPI | D21: CPI Headline e Core | E21: FRED (BLS) | F21: CPIAUCSL / CPILFESL | G21: Mensal | H21: Índice | I21: Índice | J21: Nível, MoM, QoQ, YoY, acum. 3/6/9/12m, 3m/6m SAAR, real/nominal | K21: EUA | L21: Verificado
A22: US-017 | B22: Inflação | C22: CPI | D22: Supercore (services less rent of shelter) | E22: FRED (BLS) | F22: CUSR0000SASL2RS | G22: Mensal | H22: Índice | I22: Índice | J22: Nível, MoM, QoQ, YoY, acum. 3/6/9/12m, 3m/6m SAAR, real/nominal | K22: EUA | L22: Verificado | M22: Proxy; supercore estrito exclui também energia
A23: US-018 | B23: Inflação | C23: CPI | D23: Rent CPI e Owner Equivalent Rent | E23: FRED (BLS) | F23: CUSR0000SEHA / CUSR0000SEHC | G23: Mensal | H23: Índice | I23: Índice | J23: Nível, MoM, QoQ, YoY, acum. 3/6/9/12m, 3m/6m SAAR, real/nominal | K23: EUA | L23: Verificado
A24: US-019 | B24: Inflação | C24: PCE | D24: PCE e Core PCE | E24: FRED (BEA) | F24: PCEPI / PCEPILFE | G24: Mensal | H24: Índice | I24: Índice | J24: Nível, MoM, QoQ, YoY, acum. 3/6/9/12m, 3m/6m SAAR, real/nominal | K24: EUA | L24: Verificado
A25: US-020 | B25: Inflação | C25: PCE | D25: Trimmed Mean PCE (Dallas Fed, 12m) | E25: FRED | F25: PCETRIM12M159SFRBDAL | G25: Mensal | H25: % | I25: Taxa | J25: Nível, Δ p.p. (MoM, YoY, 3/6/12m) | K25: EUA | L25: Verificado
A26: US-021 | B26: Inflação | C26: PPI | D26: PPI Final Demand | E26: FRED (BLS) | F26: PPIFIS | G26: Mensal | H26: Índice | I26: Índice | J26: Nível, MoM, QoQ, YoY, acum. 3/6/9/12m, 3m/6m SAAR, real/nominal | K26: EUA | L26: Verificado
A27: US-022 | B27: Inflação | C27: Expectativas | D27: 5y5y Forward Inflation Expectation | E27: FRED | F27: T5YIFR | G27: Diária | H27: % | I27: Taxa | J27: Nível, Δ p.p. (MoM, YoY, 3/6/12m) | K27: EUA | L27: Verificado | M27: Substitui o FRA 5Y5Y SOFR
A28: US-023 | B28: Inflação | C28: Expectativas | D28: FRA 5Y5Y SOFR / inflation swaps | E28: Bloomberg | F28: — | G28: Diária | H28: % | I28: Taxa | J28: Nível, Δ p.p. (MoM, YoY, 3/6/12m) | K28: v2 | L28: Pago | M28: Usar T5YIFR
A29: US-024 | B29: Inflação | C29: Expectativas | D29: Michigan 1y inflation expectations | E29: FRED | F29: MICH | G29: Mensal | H29: % | I29: Taxa | J29: Nível, Δ p.p. (MoM, YoY, 3/6/12m) | K29: EUA | L29: Verificado | M29: Adicionado
A30: US-025 | B30: Inflação | C30: Antecedentes | D30: Manheim Used Vehicle Value Index | E30: Cox Automotive | F30: Download (site) | G30: Mensal | H30: Índice | I30: Índice | J30: Nível, MoM, QoQ, YoY, acum. 3/6/9/12m, 3m/6m SAAR, real/nominal | K30: v2 | L30: Sem API
A31: US-026 | B31: Inflação | C31: Antecedentes | D31: Container freight (Drewry / Freightos) | E31: Drewry / Freightos | F31: — | G31: Semanal | H31: US$/FEU | I31: Índice | J31: Nível, MoM, QoQ, YoY, acum. 3/6/9/12m, 3m/6m SAAR, real/nominal | K31: v2 | L31: Pago
A32: US-027 | B32: Atividade | C32: PIB | D32: Real GDP (nível, QoQ SAAR) | E32: FRED (BEA) | F32: GDPC1 / A191RL1Q225SBEA | G32: Trimestral | H32: US$ bi 2017 | I32: Índice | J32: Nível, MoM, QoQ, YoY, acum. 3/6/9/12m, 3m/6m SAAR, real/nominal | K32: EUA | L32: Verificado
A33: US-028 | B33: Atividade | C33: PIB | D33: Real GDP change (US$ tri) × Unemployment | E33: Argus | F33: Δ GDPC1 × UNRATE | G33: Trimestral | H33: US$ tri | I33: Derivado | J33: Conforme definição da fórmula | K33: EUA | L33: Derivado
A34: US-029 | B34: Atividade | C34: PIB | D34: GDP goods × services | E34: BEA API | F34: NIPA T10206 | G34: Trimestral | H34: US$ bi | I34: Índice | J34: Nível, MoM, QoQ, YoY, acum. 3/6/9/12m, 3m/6m SAAR, real/nominal | K34: v2 | L34: Confirmar
A35: US-030 | B35: Atividade | C35: PIB | D35: GDPNow | E35: FRED (Atlanta Fed) | F35: GDPNOW | G35: Contínua | H35: % SAAR | I35: Taxa | J35: Nível, Δ p.p. (MoM, YoY, 3/6/12m) | K35: EUA | L35: Verificado | M35: 3,7% para 3T26 na verificação
A36: US-031 | B36: Atividade | C36: Consumo | D36: Retail Sales (nominal e real) | E36: FRED (Census) | F36: RSAFS / RRSFS | G36: Mensal | H36: US$ mi | I36: Fluxo | J36: Nível, soma 3/12m, MoM % (SA), YoY %, real/nominal, % PIB | K36: EUA | L36: Verificado
A37: US-032 | B37: Atividade | C37: Consumo | D37: Real PCE e Private Consumption YoY | E37: FRED (BEA) | F37: PCEC96 | G37: Mensal | H37: US$ bi | I37: Fluxo | J37: Nível, soma 3/12m, MoM % (SA), YoY %, real/nominal, % PIB | K37: EUA | L37: Verificado
A38: US-033 | B38: Atividade | C38: Vendas | D38: Wholesale Sales | E38: FRED (Census) | F38: A mapear | G38: Mensal | H38: US$ mi | I38: Fluxo | J38: Nível, soma 3/12m, MoM % (SA), YoY %, real/nominal, % PIB | K38: v2 | L38: A mapear
A39: US-034 | B39: Atividade | C39: Vendas | D39: Selected Services Revenue | E39: Census QSS | F39: API Census | G39: Trimestral | H39: US$ mi | I39: Fluxo | J39: Nível, soma 3/12m, MoM % (SA), YoY %, real/nominal, % PIB | K39: v2 | L39: Confirmar
A40: US-035 | B40: Atividade | C40: Estoques | D40: Change in Private Inventories | E40: FRED (BEA) | F40: CBIC1 | G40: Trimestral | H40: US$ bi | I40: Fluxo | J40: Nível, soma 3/12m, MoM % (SA), YoY %, real/nominal, % PIB | K40: EUA | L40: Verificado
A41: US-036 | B41: Atividade | C41: Estoques | D41: Manufacturers Inventories/Sales | E41: FRED (Census) | F41: MNFCTRIRSA | G41: Mensal | H41: x | I41: Taxa | J41: Nível, Δ p.p. (MoM, YoY, 3/6/12m) | K41: EUA | L41: Verificado | M41: Proxy para excess inventory
A42: US-037 | B42: Atividade | C42: Indústria | D42: Industrial Production | E42: FRED (Fed) | F42: INDPRO | G42: Mensal | H42: Índice | I42: Índice | J42: Nível, MoM, QoQ, YoY, acum. 3/6/9/12m, 3m/6m SAAR, real/nominal | K42: EUA | L42: Verificado | M42: Adicionado
A43: US-038 | B43: Atividade | C43: PMI | D43: ISM Manufacturing e Services PMI | E43: ISM | F43: — | G43: Mensal | H43: Índice | I43: Índice | J43: Nível, MoM, QoQ, YoY, acum. 3/6/9/12m, 3m/6m SAAR, real/nominal | K43: v2 | L43: Pago | M43: Licenciado; saiu do FRED
A44: US-039 | B44: Atividade | C44: PMI | D44: Pesquisas regionais do Fed (Philly, Empire, Dallas) | E44: FRED | F44: GACDFSA e equivalentes | G44: Mensal | H44: Índice | I44: Índice | J44: Nível, MoM, QoQ, YoY, acum. 3/6/9/12m, 3m/6m SAAR, real/nominal | K44: EUA | L44: A mapear | M44: Código GACDFSA não existe no FRED (HTTP 400 na validação de 2026-10-04); localizar o código correto
A45: US-040 | B45: Fed & Juros | C45: Política | D45: Fed Funds (efetivo e banda) | E45: FRED | F45: DFF / DFEDTARU / DFEDTARL | G45: Diária | H45: % | I45: Taxa | J45: Nível, Δ p.p. (MoM, YoY, 3/6/12m) | K45: EUA | L45: Verificado
A46: US-041 | B46: Fed & Juros | C46: Balanço | D46: Total Fed Assets | E46: FRED | F46: WALCL | G46: Semanal | H46: US$ mi | I46: Estoque | J46: Nível, MoM %, YoY %, real/nominal, % PIB | K46: EUA | L46: Verificado
A47: US-042 | B47: Fed & Juros | C47: Comunicação | D47: Press releases e statements do FOMC | E47: Federal Reserve | F47: RSS | G47: Por evento | H47: Texto | I47: Texto | J47: — | K47: EUA | L47: Confirmar | M47: Alimenta o agregador
A48: US-043 | B48: Fed & Juros | C48: Projeções | D48: Dotplot (mediana SEP) | E48: FRED | F48: FEDTARMD (+ FEDTARRH/RL) | G48: Trimestral | H48: % | I48: Taxa | J48: Nível, Δ p.p. (MoM, YoY, 3/6/12m) | K48: EUA | L48: Verificado | M48: Atualizado em 16/09/2026
A49: US-044 | B49: Fed & Juros | C49: Curva | D49: US Yield Curve (1m–30y) e spreads | E49: FRED | F49: DGS1MO…DGS30 / T10Y2Y / T10Y3M | G49: Diária | H49: % | I49: Taxa | J49: Nível, Δ p.p. (MoM, YoY, 3/6/12m) | K49: EUA | L49: Verificado
A50: US-045 | B50: Fed & Juros | C50: Curva | D50: SOFR overnight | E50: FRED | F50: SOFR | G50: Diária | H50: % | I50: Taxa | J50: Nível, Δ p.p. (MoM, YoY, 3/6/12m) | K50: EUA | L50: Verificado
A51: US-046 | B51: Fed & Juros | C51: Curva | D51: SOFR 10Y swap | E51: Bloomberg | F51: — | G51: Diária | H51: % | I51: Taxa | J51: Nível, Δ p.p. (MoM, YoY, 3/6/12m) | K51: v2 | L51: Pago
A52: US-047 | B52: Fed & Juros | C52: Mercado | D52: WIRP / probabilidade implícita | E52: Bloomberg / CME FedWatch | F52: — | G52: Diária | H52: % | I52: Taxa | J52: Nível, Δ p.p. (MoM, YoY, 3/6/12m) | K52: v2 | L52: Pago | M52: FedWatch só no site
A53: US-048 | B53: Fed & Juros | C53: Crédito | D53: Mortgage Rate 30y | E53: FRED (Freddie Mac) | F53: MORTGAGE30US | G53: Semanal | H53: % | I53: Taxa | J53: Nível, Δ p.p. (MoM, YoY, 3/6/12m) | K53: EUA | L53: Verificado
A54: US-049 | B54: Fed & Juros | C54: Agregados | D54: M1 e M2 | E54: FRED | F54: M1SL / M2SL | G54: Mensal | H54: US$ bi | I54: Estoque | J54: Nível, MoM %, YoY %, real/nominal, % PIB | K54: EUA | L54: Verificado
A55: US-050 | B55: Fed & Juros | C55: Agregados | D55: M3 e M4 | E55: Center for Financial Stability (Divisia) | F55: Download | G55: Mensal | H55: US$ bi | I55: Estoque | J55: Nível, MoM %, YoY %, real/nominal, % PIB | K55: v2 | L55: Sem API | M55: Fed descontinuou o M3 em 2006
A56: US-051 | B56: Fed & Juros | C56: Condições | D56: Chicago Fed NFCI | E56: FRED | F56: NFCI | G56: Semanal | H56: Índice | I56: Índice | J56: Nível, MoM, QoQ, YoY, acum. 3/6/9/12m, 3m/6m SAAR, real/nominal | K56: EUA | L56: Verificado
A57: US-052 | B57: Fed & Juros | C57: Condições | D57: St. Louis Fed Financial Stress Index | E57: FRED | F57: STLFSI4 | G57: Semanal | H57: Índice | I57: Índice | J57: Nível, MoM, QoQ, YoY, acum. 3/6/9/12m, 3m/6m SAAR, real/nominal | K57: EUA | L57: Verificado
A58: US-053 | B58: Fed & Juros | C58: Crédito | D58: SLOOS — net % tightening C&I | E58: FRED | F58: DRTSCILM | G58: Trimestral | H58: % | I58: Taxa | J58: Nível, Δ p.p. (MoM, YoY, 3/6/12m) | K58: EUA | L58: Verificado
A59: US-054 | B59: Fed & Juros | C59: Dívida | D59: % da dívida federal detida pelo Fed | E59: Argus | F59: FDHBFRBN / GFDEBTN | G59: Trimestral | H59: % | I59: Derivado | J59: Conforme definição da fórmula | K59: EUA | L59: Derivado
A60: US-055 | B60: Imobiliário | C60: Preços | D60: Median Sales Price e Case-Shiller | E60: FRED | F60: MSPUS / CSUSHPISA | G60: Mensal/Trim. | H60: US$ / Índice | I60: Índice | J60: Nível, MoM, QoQ, YoY, acum. 3/6/9/12m, 3m/6m SAAR, real/nominal | K60: EUA | L60: Verificado | M60: Case-Shiller adicionado
A61: US-056 | B61: Imobiliário | C61: Oferta | D61: Months' Supply, Starts, Permits, Completions | E61: FRED (Census) | F61: MSACSR / HOUST / PERMIT / COMPUTSA | G61: Mensal | H61: Mil / meses | I61: Fluxo | J61: Nível, soma 3/12m, MoM % (SA), YoY %, real/nominal, % PIB | K61: EUA | L61: Verificado
A62: US-057 | B62: Imobiliário | C62: Vendas | D62: Existing e Pending Home Sales | E62: NAR | F62: EXHOSLUSM495S (histórico curto) | G62: Mensal | H62: Mil | I62: Fluxo | J62: Nível, soma 3/12m, MoM % (SA), YoY %, real/nominal, % PIB | K62: v2 | L62: Pago | M62: FRED exibe só os últimos meses por licença
A63: US-058 | B63: Imobiliário | C63: Vacância | D63: Rental e Homeowner Vacancy | E63: FRED (Census) | F63: RRVRUSQ156N / RHVRUSQ156N | G63: Trimestral | H63: % | I63: Taxa | J63: Nível, Δ p.p. (MoM, YoY, 3/6/12m) | K63: EUA | L63: Verificado
A64: US-059 | B64: Imobiliário | C64: Sentimento | D64: NAHB Housing Market Index | E64: NAHB | F64: Download (site) | G64: Mensal | H64: Índice | I64: Índice | J64: Nível, MoM, QoQ, YoY, acum. 3/6/9/12m, 3m/6m SAAR, real/nominal | K64: v2 | L64: Sem API
A65: US-060 | B65: Imobiliário | C65: Acessibilidade | D65: Housing Affordability Index | E65: NAR / FRED | F65: FIXHAI | G65: Mensal | H65: Índice | I65: Índice | J65: Nível, MoM, QoQ, YoY, acum. 3/6/9/12m, 3m/6m SAAR, real/nominal | K65: v2 | L65: Confirmar
A66: US-061 | B66: Imobiliário | C66: Crédito | D66: Mortgage LTV | E66: FHFA / ICE | F66: — | G66: Trimestral | H66: % | I66: Taxa | J66: Nível, Δ p.p. (MoM, YoY, 3/6/12m) | K66: v2 | L66: Sem API
A67: US-062 | B67: Consumidor | C67: Confiança | D67: Michigan Consumer Sentiment | E67: FRED | F67: UMCSENT | G67: Mensal | H67: Índice | I67: Índice | J67: Nível, MoM, QoQ, YoY, acum. 3/6/9/12m, 3m/6m SAAR, real/nominal | K67: EUA | L67: Verificado | M67: Substitui Conference Board (pago)
A68: US-063 | B68: Consumidor | C68: Confiança | D68: Small Business Optimism (NFIB) | E68: NFIB | F68: Relatório (PDF) | G68: Mensal | H68: Índice | I68: Índice | J68: Nível, MoM, QoQ, YoY, acum. 3/6/9/12m, 3m/6m SAAR, real/nominal | K68: v2 | L68: Sem API
A69: US-064 | B69: Consumidor | C69: Balanço | D69: Household Net Worth | E69: FRED (Z.1) | F69: TNWBSHNO | G69: Trimestral | H69: US$ bi | I69: Estoque | J69: Nível, MoM %, YoY %, real/nominal, % PIB | K69: EUA | L69: Verificado
A70: US-065 | B70: Consumidor | C70: Renda | D70: Personal Saving Rate e Real Disposable Income | E70: FRED (BEA) | F70: PSAVERT / DSPIC96 | G70: Mensal | H70: % / US$ bi | I70: Taxa | J70: Nível, Δ p.p. (MoM, YoY, 3/6/12m) | K70: EUA | L70: Verificado
A71: US-066 | B71: Consumidor | C71: Balanço | D71: Liabilities/Assets | E71: Argus | F71: Z.1 passivos / ativos | G71: Trimestral | H71: % | I71: Derivado | J71: Conforme definição da fórmula | K71: EUA | L71: Derivado
A72: US-067 | B72: Consumidor | C72: Balanço | D72: Debt Service % DPI | E72: FRED | F72: TDSP | G72: Trimestral | H72: % | I72: Taxa | J72: Nível, Δ p.p. (MoM, YoY, 3/6/12m) | K72: EUA | L72: Verificado
A73: US-068 | B73: Consumidor | C73: Desigualdade | D73: Assets by Wealth Percentile | E73: Fed DFA | F73: Download CSV / FRED (séries DFA) | G73: Trimestral | H73: % | I73: Taxa | J73: Nível, Δ p.p. (MoM, YoY, 3/6/12m) | K73: v2 | L73: Confirmar
A74: US-069 | B74: Consumidor | C74: Crédito | D74: Credit Card / Revolving Credit | E74: FRED (G.19) | F74: REVOLSL | G74: Mensal | H74: US$ bi | I74: Estoque | J74: Nível, MoM %, YoY %, real/nominal, % PIB | K74: EUA | L74: Verificado
A75: US-070 | B75: Consumidor | C75: Crédito | D75: Expected application rate (cartão) | E75: NY Fed SCE | F75: Download | G75: Quadrimestral | H75: % | I75: Taxa | J75: Nível, Δ p.p. (MoM, YoY, 3/6/12m) | K75: v2 | L75: Sem API
A76: US-071 | B76: Consumidor | C76: Crédito | D76: Delinquencies (all loans e cartões) | E76: FRED | F76: DRALACBS / DRCCLACBS | G76: Trimestral | H76: % | I76: Taxa | J76: Nível, Δ p.p. (MoM, YoY, 3/6/12m) | K76: EUA | L76: Verificado
A77: US-072 | B77: Corporativo | C77: Lucros | D77: Corporate Profits | E77: FRED (BEA) | F77: CP | G77: Trimestral | H77: US$ bi | I77: Fluxo | J77: Nível, soma 3/12m, MoM % (SA), YoY %, real/nominal, % PIB | K77: EUA | L77: Confirmar
A78: US-073 | B78: Corporativo | C78: Lucros | D78: Corporate Profits × S&P 500 | E78: Argus + FMP | F78: CP × ^GSPC | G78: Trimestral | H78: Índice | I78: Derivado | J78: Conforme definição da fórmula | K78: EUA | L78: Derivado | M78: S&P 500 no FRED tem só 10 anos
A79: US-074 | B79: Corporativo | C79: Lucros | D79: EPS estimates S&P 500 | E79: S&P DJI / FactSet | F79: xlsx S&P (manual) | G79: Trimestral | H79: US$ | I79: Fluxo | J79: Nível, soma 3/12m, MoM % (SA), YoY %, real/nominal, % PIB | K79: v2 | L79: Sem API
A80: US-075 | B80: Corporativo | C80: Valuation | D80: Market Cap to GDP (Buffett) | E80: Argus | F80: NCBEILQ027S / GDP | G80: Trimestral | H80: % | I80: Derivado | J80: Conforme definição da fórmula | K80: EUA | L80: Derivado
A81: US-076 | B81: Corporativo | C81: Investimento | D81: Fixed Investment (privado não residencial) | E81: FRED (BEA) | F81: PNFIC1 | G81: Trimestral | H81: US$ bi | I81: Fluxo | J81: Nível, soma 3/12m, MoM % (SA), YoY %, real/nominal, % PIB | K81: EUA | L81: Verificado
A82: US-077 | B82: Corporativo | C82: Investimento | D82: Capex Plans (NFIB e Fed regionais) | E82: NFIB / Fed regionais | F82: PDF / FRED | G82: Mensal | H82: % | I82: Taxa | J82: Nível, Δ p.p. (MoM, YoY, 3/6/12m) | K82: v2 | L82: Sem API
A83: US-078 | B83: Corporativo | C83: Caixa | D83: Corporate cash on hand | E83: FRED (Z.1) | F83: A mapear | G83: Trimestral | H83: US$ bi | I83: Estoque | J83: Nível, MoM %, YoY %, real/nominal, % PIB | K83: v2 | L83: A mapear
A84: US-079 | B84: Corporativo | C84: Stress | D84: Bankruptcy index | E84: Bloomberg / US Courts | F84: — | G84: Mensal | H84: Nº | I84: Fluxo | J84: Nível, soma 3/12m, MoM % (SA), YoY %, real/nominal, % PIB | K84: v2 | L84: Pago | M84: US Courts publica estatística trimestral gratuita
A85: US-080 | B85: Setor Externo & Fiscal | C85: Dívida | D85: Federal Debt % GDP | E85: FRED | F85: GFDEGDQ188S | G85: Trimestral | H85: % | I85: Taxa | J85: Nível, Δ p.p. (MoM, YoY, 3/6/12m) | K85: EUA | L85: Verificado
A86: US-081 | B86: Setor Externo & Fiscal | C86: Projeções | D86: CBO deficit projections | E86: CBO | F86: xlsx (manual) | G86: Semestral | H86: % PIB | I86: Taxa | J86: Nível, Δ p.p. (MoM, YoY, 3/6/12m) | K86: v2 | L86: Sem API
A87: US-082 | B87: Setor Externo & Fiscal | C87: Projeções | D87: Deficit impact e spending revisions (Kinea) | E87: Kinea | F87: Relatórios (manual) | G87: Eventual | H87: % PIB | I87: Taxa | J87: Nível, Δ p.p. (MoM, YoY, 3/6/12m) | K87: v2 | L87: Sem API | M87: Fonte de terceiro; registrar data do relatório
A88: US-083 | B88: Setor Externo & Fiscal | C88: Comércio | D88: Trade Balance | E88: FRED (Census) | F88: BOPGSTB | G88: Mensal | H88: US$ mi | I88: Fluxo | J88: Nível, soma 3/12m, MoM % (SA), YoY %, real/nominal, % PIB | K88: EUA | L88: Verificado
A89: US-084 | B89: Setor Externo & Fiscal | C89: Comércio | D89: Current Account % GDP | E89: Argus | F89: IEABC / GDP | G89: Trimestral | H89: % | I89: Derivado | J89: Conforme definição da fórmula | K89: EUA | L89: Derivado
A90: US-085 | B90: Setor Externo & Fiscal | C90: Comércio | D90: Imports — automotive (end-use) | E90: Census API | F90: FT-900 end-use | G90: Mensal | H90: US$ mi | I90: Fluxo | J90: Nível, soma 3/12m, MoM % (SA), YoY %, real/nominal, % PIB | K90: v2 | L90: Confirmar
A91: US-086 | B91: Setor Externo & Fiscal | C91: Comércio | D91: Effective tariff rate | E91: Argus | F91: B235RC1Q027SBEA / IMPGS | G91: Trimestral | H91: % | I91: Derivado | J91: Conforme definição da fórmula | K91: EUA | L91: Derivado | M91: Customs duties / importações
A92: US-087 | B92: Setor Externo & Fiscal | C92: Energia | D92: Strategic Petroleum Reserve | E92: FRED (EIA) | F92: WCSSTUS1 | G92: Semanal | H92: Mil barris | I92: Estoque | J92: Nível, MoM %, YoY %, real/nominal, % PIB | K92: EUA | L92: A mapear | M92: Código WCSSTUS1 não existe no FRED (HTTP 400 na validação de 2026-10-04); localizar o código correto
A93: US-088 | B93: Setor Externo & Fiscal | C93: Câmbio | D93: DXY | E93: ICE | F93: — | G93: Diária | H93: Índice | I93: Índice | J93: Nível, MoM, QoQ, YoY, acum. 3/6/9/12m, 3m/6m SAAR, real/nominal | K93: v2 | L93: Pago | M93: Usar DTWEXBGS (broad dollar, FRED)
A94: US-089 | B94: Setor Externo & Fiscal | C94: Câmbio | D94: Broad Dollar Index | E94: FRED | F94: DTWEXBGS | G94: Diária | H94: Índice | I94: Índice | J94: Nível, MoM, QoQ, YoY, acum. 3/6/9/12m, 3m/6m SAAR, real/nominal | K94: EUA | L94: Verificado | M94: Substituto do DXY
A95: US-090 | B95: Risco & Mercado | C95: Vol | D95: VIX | E95: FRED (CBOE) | F95: VIXCLS | G95: Diária | H95: Índice | I95: Índice | J95: Nível, MoM, QoQ, YoY, acum. 3/6/9/12m, 3m/6m SAAR, real/nominal | K95: EUA | L95: Verificado
A96: US-091 | B96: Risco & Mercado | C96: Vol | D96: MOVE Index | E96: ICE | F96: — | G96: Diária | H96: Índice | I96: Índice | J96: Nível, MoM, QoQ, YoY, acum. 3/6/9/12m, 3m/6m SAAR, real/nominal | K96: v2 | L96: Pago
A97: US-092 | B97: Risco & Mercado | C97: Crédito | D97: ICE BofA High Yield OAS | E97: FRED | F97: BAMLH0A0HYM2 | G97: Diária | H97: % | I97: Taxa | J97: Nível, Δ p.p. (MoM, YoY, 3/6/12m) | K97: EUA | L97: Verificado | M97: Conferir profundidade do histórico disponível
A98: US-093 | B98: Risco & Mercado | C98: Valuation | D98: Equity Risk Premium | E98: Argus / Damodaran | F98: Earnings yield − DFII10 | G98: Mensal | H98: % | I98: Derivado | J98: Conforme definição da fórmula | K98: EUA | L98: Derivado
A99: US-094 | B99: Risco & Mercado | C99: Crédito | D99: Implied Default (a partir do HY spread) | E99: Argus | F99: f(BAMLH0A0HYM2, recovery) | G99: Diária | H99: % | I99: Derivado | J99: Conforme definição da fórmula | K99: EUA | L99: Derivado
A100: US-095 | B100: Risco & Mercado | C100: Recessão | D100: Recession probability (Piger) | E100: FRED | F100: RECPROUSM156N | G100: Mensal | H100: % | I100: Taxa | J100: Nível, Δ p.p. (MoM, YoY, 3/6/12m) | K100: EUA | L100: Verificado
A101: US-096 | B101: Risco & Mercado | C101: Bolsa | D101: Russell 2000 | E101: FMP | F101: ^RUT / IWM | G101: Diária | H101: Pontos | I101: Índice | J101: Nível, MoM, QoQ, YoY, acum. 3/6/9/12m, 3m/6m SAAR, real/nominal | K101: EUA | L101: Confirmar | M101: Não está no FRED

Sheet Central
A1: Aba Central — Command Center e notícias
A2: O que aparece na primeira tela e de onde vem.
A5: Bloco | B5: Componente | C5: Conteúdo | D5: Fonte | E5: Fase | F5: Observação
A6: Faixa de mercado | B6: Ticker no topo | C6: Ibovespa, USD/BRL, S&P 500, UST 10Y, Broad Dollar, Brent, ouro, VIX | D6: FMP + FRED + BCB SGS | E6: MVP | F6: Atualização diária; intraday só com plano pago
A7: Regime | B7: Cartões Brasil | C7: Selic × neutro implícito, IPCA 12m × meta, desocupação, Focus IPCA/Selic | D7: Abas Brasil (derivados) | E7: MVP | F7: Cada cartão leva à aba de origem
A8: Regime | B8: Cartões EUA | C8: Fed funds, Core PCE, desemprego, curva 10y-2y, GDPNow | D8: Aba EUA | E8: EUA
A9: Agenda | B9: Próximos 7 dias | C9: Divulgações do IBGE, BCB, BLS/BEA; reuniões de Copom e FOMC | D9: IBGE API de calendário + FRED releases + curado | E9: MVP | F9: Calendário de Copom/FOMC curado manualmente
A10: Última divulgação | B10: O que saiu | C10: Último dado × anterior × Focus (quando houver) | D10: Derivado | E10: MVP | F10: Consenso para os EUA não tem fonte gratuita
A11: Notícias | B11: Feed oficial | C11: Comunicados e notas de BCB, Fed, Tesouro, IBGE (Agência de Notícias) | D11: RSS oficiais | E11: MVP | F11: Fonte primária, zero risco jurídico
A12: Notícias | B12: Feed de imprensa | C12: Manchetes de veículos selecionados (título + link) | D12: RSS de veículos + Google News RSS por consulta | E12: MVP | F12: Só título, fonte e link; marcação por país/tema via palavra-chave
A13: Notícias | B13: Eventos globais | C13: Volume de notícias por país/tema (geopolítica) | D13: GDELT DOC API | E13: v2
A14: Notícias | B14: Resumo do dia | C14: Síntese automática das notícias por tema | D14: Claude API (modelo leve) | E14: v2 | F14: Custo de API: alguns US$/mês
A15: Monitor | B15: Saúde dos dados | C15: Fontes com falha ou atrasadas | D15: Tabela ingestion_runs | E15: MVP
A16: Monitor | B16: Teses | C16: Teses ativas e gatilhos próximos de disparar | D16: Aba Teses | E16: v2
A17: Monitor | B17: Alertas | C17: Alertas disparados nas últimas 24h | D17: Motor de alertas | E17: v3

Sheet Fontes
A1: Registro de fontes
A2: Cada fonte vira um adapter isolado no pipeline.
A5: Fonte | B5: Acesso | C5: Autenticação | D5: Limite / observação | E5: Risco técnico | F5: Custo
A6: BCB SGS | B6: REST JSON/CSV (api.bcb.gov.br) | C6: Nenhuma | D6: Séries diárias: máx. 10 anos por consulta (fatiar janela) | E6: Médio | F6: Grátis
A7: BCB Olinda — Focus | B7: OData REST | C7: Nenhuma | D7: Filtros OData obrigatórios para volume grande | E7: Médio | F7: Grátis
A8: BCB Portal de Dados Abertos | B8: Site / CKAN | C8: Nenhuma | D8: Limita requisições em rajada (429 observado) | E8: Médio | F8: Grátis
A9: IBGE SIDRA | B9: REST (apisidra.ibge.gov.br) | C9: Nenhuma | D9: Sintaxe verbosa; tabelas mudam de número em revisões de base | E9: Médio | F9: Grátis
A10: IBGE API de calendário | B10: REST (servicodados.ibge.gov.br) | C10: Nenhuma | D10: Agenda de divulgações | E10: Baixo | F10: Grátis
A11: ComexStat (MDIC) | B11: REST | C11: Nenhuma | D11: Consultas por NCM, país, período | E11: Médio | F11: Grátis
A12: Tesouro Transparente | B12: API Séries Temporais (RTN, JSON) · CKAN / xlsx | C12: Nenhuma | D12: RTN por API JSON paginada (decisão 0010); RMD ainda em planilha | E12: Baixo | F12: Grátis
A13: Ipeadata | B13: OData REST | C13: Nenhuma | D13: Agrega séries de terceiros; conferir atualização | E13: Médio | F13: Grátis
A14: Câmara / Senado Dados Abertos | B14: REST | C14: Nenhuma | D14: — | E14: Baixo | F14: Grátis
A15: TSE Dados Abertos | B15: CSV | C15: Nenhuma | D15: Arquivos grandes por eleição | E15: Baixo | F15: Grátis
A16: ANBIMA / B3 | B16: Arquivos diários no site | C16: Nenhuma (API ANBIMA é paga) | D16: Formatos mudam sem aviso | E16: Alto | F16: Grátis / pago
... A25: BCB site (API Copom) | B25: JSON (www.bcb.gov.br/api/servico/sitebcb) | C25: Nenhuma | D25: Não documentada; comunicados e atas do Copom | E25: Médio | F25: Grátis
